CodonTransformer/__init__.py
CodonTransformer/CodonData.py
CodonTransformer/CodonEvaluation.py
CodonTransformer/CodonJupyter.py
CodonTransformer/CodonPrediction.py
CodonTransformer/CodonUtils.py
codontransformer-1.6.7.dist-info/LICENSE
codontransformer-1.6.7.dist-info/METADATA
codontransformer-1.6.7.dist-info/WHEEL
codontransformer-1.6.7.dist-info/RECORD
