Metadata-Version: 2.3
Name: CodonTransformer
Version: 1.6.7
Summary: The ultimate tool for codon optimization, transforming protein sequences into optimized DNA sequences specific for your target organisms.
License: Apache-2.0
Author: Adibvafa Fallahpour
Author-email: Adibvafa.fallahpour@mail.utoronto.ca
Requires-Python: >=3.9,<4.0
Classifier: License :: OSI Approved :: Apache Software License
Classifier: Operating System :: OS Independent
Classifier: Programming Language :: Python :: 3
Classifier: Programming Language :: Python :: 3.9
Classifier: Programming Language :: Python :: 3.10
Classifier: Programming Language :: Python :: 3.11
Classifier: Programming Language :: Python :: 3.12
Classifier: Programming Language :: Python :: 3.13
Requires-Dist: CAI-PyPI (>=2.0.1,<3.0.0)
Requires-Dist: biopython (>=1.83,<2.0)
Requires-Dist: ipywidgets (>=7.0.0,<8.0.0)
Requires-Dist: numpy (<2.0.0)
Requires-Dist: onnxruntime (>=1.17.3,<2.0.0)
Requires-Dist: pandas (>=2.0.0,<3.0.0)
Requires-Dist: python_codon_tables (>=0.1.12,<0.2.0)
Requires-Dist: pytorch_lightning (>=2.2.1,<3.0.0)
Requires-Dist: scikit-learn (>=1.2.2,<2.0.0)
Requires-Dist: scipy (>=1.13.1,<2.0.0)
Requires-Dist: setuptools (>=70.0.0,<71.0.0)
Requires-Dist: torch (>=2.0.0,<3.0.0)
Requires-Dist: tqdm (>=4.66.2,<5.0.0)
Requires-Dist: transformers (>=4.40.0,<5.0.0)
Project-URL: Homepage, https://github.com/adibvafa/CodonTransformer
Project-URL: Repository, https://github.com/adibvafa/CodonTransformer
